kh2rando/__init__.py
kh2rando/__main__.py
kh2rando/seed_gen_cli.py
kh2rando/seed_gen/__init__.py
kh2rando/seed_gen/generator.py
kh2rando/seed_gen/Class/__init__.py
kh2rando/seed_gen/Class/exceptions.py
kh2rando/seed_gen/Class/itemClass.py
kh2rando/seed_gen/Class/newLocationClass.py
kh2rando/seed_gen/Class/openkhmod.py
kh2rando/seed_gen/Class/randomUtils.py
kh2rando/seed_gen/Class/seedSettings.py
kh2rando/seed_gen/Class/settingkey.py
kh2rando/seed_gen/List/ChestList.py
kh2rando/seed_gen/List/DropRateIds.py
kh2rando/seed_gen/List/ItemList.py
kh2rando/seed_gen/List/LvupStats.py
kh2rando/seed_gen/List/NewLocationList.py
kh2rando/seed_gen/List/ObjectiveList.py
kh2rando/seed_gen/List/configDict.py
kh2rando/seed_gen/List/experienceValues.py
kh2rando/seed_gen/List/hashTextEntries.py
kh2rando/seed_gen/List/inventory/ability.py
kh2rando/seed_gen/List/inventory/accessory.py
kh2rando/seed_gen/List/inventory/armor.py
kh2rando/seed_gen/List/inventory/bonus.py
kh2rando/seed_gen/List/inventory/consumable.py
kh2rando/seed_gen/List/inventory/form.py
kh2rando/seed_gen/List/inventory/growth.py
kh2rando/seed_gen/List/inventory/item.py
kh2rando/seed_gen/List/inventory/keyblade.py
kh2rando/seed_gen/List/inventory/magic.py
kh2rando/seed_gen/List/inventory/map.py
kh2rando/seed_gen/List/inventory/misc.py
kh2rando/seed_gen/List/inventory/pieces.py
kh2rando/seed_gen/List/inventory/proof.py
kh2rando/seed_gen/List/inventory/recipe.py
kh2rando/seed_gen/List/inventory/report.py
kh2rando/seed_gen/List/inventory/shield.py
kh2rando/seed_gen/List/inventory/staff.py
kh2rando/seed_gen/List/inventory/storyunlock.py
kh2rando/seed_gen/List/inventory/summon.py
kh2rando/seed_gen/List/inventory/synth.py
kh2rando/seed_gen/List/location/agrabah.py
kh2rando/seed_gen/List/location/atlantica.py
kh2rando/seed_gen/List/location/beastscastle.py
kh2rando/seed_gen/List/location/disneycastle.py
kh2rando/seed_gen/List/location/donaldbonus.py
kh2rando/seed_gen/List/location/formlevel.py
kh2rando-0.0.8.dist-info/licenses/LICENSE
kh2rando-0.0.8.dist-info/METADATA
kh2rando-0.0.8.dist-info/WHEEL
kh2rando-0.0.8.dist-info/entry_points.txt
kh2rando-0.0.8.dist-info/top_level.txt
kh2rando-0.0.8.dist-info/RECORD
